{
  "users": [
    {
      "id": 1,
      "firstName": "James",
      "lastname": "Decker",
      "email": "james.decker@jamesdecker.com",
      "password": 1234
    }
  ],
  "photoAlbums": [
    {
      "id": 1,
      "userId": 1,
      "title": "1234 Turn Down Ln",
      "description": "large house on 4 acres"
    },
    {
      "title": "First Tour",
      "description": "This might work?!?!",
      "id": 2
    },
    {
      "title": "2nd Tour",
      "description": "Add images",
      "id": 3
    },
    {
      "title": "new tour",
      "description": "asdfasdf",
      "userId": 1,
      "id": 4
    },
    {
      "title": "user2",
      "description": "User 2 Tour",
      "userId": 2,
      "id": 5
    },
    {
      "title": "test",
      "description": "asdf",
      "userId": 1,
      "id": 6
    },
    {
      "title": "First Tour",
      "description": "asdf",
      "userId": 1,
      "id": 7
    },
    {
      "title": "Examples",
      "description": "ads",
      "userId": 1,
      "id": 8
    }
  ],
  "360images": [
    {
      "id": 1,
      "albumId": 1,
      "name": "Living Room",
      "description": "300 sqft",
      "url": "https://res.cloudinary.com/duo4xxmj8/image/upload/v1592235044/360imgFolder/living_room_mmyzrt.jpg"
    },
    {
      "userId": 1,
      "albumId": 8,
      "name": "downstairs room",
      "description": "its big",
      "url": "",
      "id": 2
    },
    {
      "userId": 1,
      "albumId": 8,
      "name": "Downstairs",
      "description": "asdfsad",
      "url": {
        "image": ""
      },
      "id": 3
    },
    {
      "userId": 1,
      "albumId": 8,
      "name": "asdfasd",
      "description": "asdfasdf",
      "url": "",
      "id": 4
    },
    {
      "userId": 1,
      "albumId": 8,
      "name": "asdf",
      "description": "asdf",
      "id": 5
    },
    {
      "userId": 1,
      "albumId": 8,
      "name": "",
      "description": "",
      "url": "",
      "id": 6
    },
    {
      "userId": 1,
      "albumId": 8,
      "name": "",
      "description": "",
      "url": {},
      "id": 7
    }
  ]
}
